encwork/__init__.py
encwork/client.py
encwork/encryption.py
encwork/exceptions.py
encwork/p2p.py
encwork/server.py
encwork/status.py
encwork-1.0.4.dist-info/LICENSE
encwork-1.0.4.dist-info/METADATA
encwork-1.0.4.dist-info/WHEEL
encwork-1.0.4.dist-info/top_level.txt
encwork-1.0.4.dist-info/RECORD
