Metadata-Version: 2.1
Name: encwork
Version: 1.0.4
Summary: RSA-encrypted networking library.
Home-page: https://github.com/MysteryBlokHed/Encwork
Author: Adam Thompson-Sharpe
Author-email: adamthompsonsharpe@gmail.com
License: UNKNOWN
Platform: UNKNOWN
Classifier: Programming Language :: Python :: 3.6
Classifier: License :: OSI Approved :: MIT License
Classifier: Operating System :: OS Independent
Requires-Python: >=3.6
Requires-Dist: cryptography (>=2.8)
